<?xml version="1.0" ?> 
<SampleConfigs>
<SampleConfig ParentNodeID = "DataSourceTypes">
  <Title>Binding to CSV Files</Title> 
  <Thumbnail>thumbnail.jpg</Thumbnail>
  <ShortBlurb>Binding to CSV Files</ShortBlurb> 
  <SampleControl>CSVDataBinding</SampleControl> 
  <InfoPages>
    <InfoPage Title="Overview">Overview.htm</InfoPage>
    <InfoPage Title="C# Source">cscode.txt</InfoPage>
    <InfoPage Title="Visual Basic Source">vbcode.txt</InfoPage>
  </InfoPages>
  <Keywords>
    <Keyword>Data, Binding to comma separated source</Keyword>
    <Keyword>Binding, comma separated</Keyword>
  </Keywords>    
</SampleConfig>



<SampleConfig ParentNodeID = "NewDataBinding">
  <Title>Binding to CSV Files</Title> 
  <Thumbnail>thumbnail.jpg</Thumbnail>
  <ShortBlurb>Binding to CSV Files</ShortBlurb> 
  <SampleControl>CSVDataBinding</SampleControl> 
  <InfoPages>
    <InfoPage Title="Overview">Overview.htm</InfoPage>
    <InfoPage Title="C# Source">cscode.txt</InfoPage>
    <InfoPage Title="Visual Basic Source">vbcode.txt</InfoPage>
  </InfoPages>
  <Keywords>
    <Keyword>Data, Binding to comma separated source</Keyword>
    <Keyword>Binding, comma separated</Keyword>
  </Keywords>    
</SampleConfig>



</SampleConfigs>
