<?xml version="1.0" standalone="yes"?>
<DataSet1 xmlns="http://tempuri.org/DataSet1.xsd">
  <xs:schema id="DataSet1" targetNamespace="http://tempuri.org/DataSet1.xsd" xmlns:mstns="http://tempuri.org/DataSet1.xsd" xmlns="http://tempuri.org/DataSet1.xsd" xmlns:xs="http://www.w3.org/2001/XMLSchema" xmlns:msdata="urn:schemas-microsoft-com:xml-msdata" attributeFormDefault="qualified" elementFormDefault="qualified">
    <xs:element name="DataSet1" msdata:IsDataSet="true" msdata:MainDataTable="http_x003A__x002F__x002F_tempuri.org_x002F_DataSet1.xsd_x003A_OrderDetails" msdata:UseCurrentLocale="true">
      <xs:complexType>
        <xs:choice minOccurs="0" maxOccurs="unbounded">
          <xs:element name="OrderDetails">
            <xs:complexType>
              <xs:sequence>
                <xs:element name="OrderID" type="xs:int" />
                <xs:element name="UnitPrice" type="xs:decimal" />
                <xs:element name="Quantity" type="xs:short" />
                <xs:element name="Discount" type="xs:float" />
                <xs:element name="ProductName">
                  <xs:simpleType>
                    <xs:restriction base="xs:string">
                      <xs:maxLength value="40" />
                    </xs:restriction>
                  </xs:simpleType>
                </xs:element>
              </xs:sequence>
            </xs:complexType>
          </xs:element>
        </xs:choice>
      </xs:complexType>
    </xs:element>
  </xs:schema>
  <OrderDetails>
    <OrderID>10643</OrderID>
    <UnitPrice>18.0000</UnitPrice>
    <Quantity>21</Quantity>
    <Discount>0.25</Discount>
    <ProductName>Chartreuse verte</ProductName>
  </OrderDetails>
  <OrderDetails>
    <OrderID>10643</OrderID>
    <UnitPrice>45.6000</UnitPrice>
    <Quantity>15</Quantity>
    <Discount>0.25</Discount>
    <ProductName>Rössle Sauerkraut</ProductName>
  </OrderDetails>
  <OrderDetails>
    <OrderID>10643</OrderID>
    <UnitPrice>12.0000</UnitPrice>
    <Quantity>2</Quantity>
    <Discount>0.25</Discount>
    <ProductName>Spegesild</ProductName>
  </OrderDetails>
  <OrderDetails>
    <OrderID>10692</OrderID>
    <UnitPrice>43.9000</UnitPrice>
    <Quantity>20</Quantity>
    <Discount>0</Discount>
    <ProductName>Vegie-spread</ProductName>
  </OrderDetails>
  <OrderDetails>
    <OrderID>10668</OrderID>
    <UnitPrice>12.5000</UnitPrice>
    <Quantity>8</Quantity>
    <Discount>0.1</Discount>
    <ProductName>Gorgonzola Telino</ProductName>
  </OrderDetails>
  <OrderDetails>
    <OrderID>10668</OrderID>
    <UnitPrice>24.0000</UnitPrice>
    <Quantity>4</Quantity>
    <Discount>0.1</Discount>
    <ProductName>Pâté chinois</ProductName>
  </OrderDetails>
  <OrderDetails>
    <OrderID>11046</OrderID>
    <UnitPrice>32.0000</UnitPrice>
    <Quantity>15</Quantity>
    <Discount>0.05</Discount>
    <ProductName>Mascarpone Fabioli</ProductName>
  </OrderDetails>
  <OrderDetails>
    <OrderID>11046</OrderID>
    <UnitPrice>38.0000</UnitPrice>
    <Quantity>20</Quantity>
    <Discount>0.05</Discount>
    <ProductName>Queso Manchego La Pastora</ProductName>
  </OrderDetails>
  <OrderDetails>
    <OrderID>11046</OrderID>
    <UnitPrice>18.0000</UnitPrice>
    <Quantity>18</Quantity>
    <Discount>0.05</Discount>
    <ProductName>Steeleye Stout</ProductName>
  </OrderDetails>
  <OrderDetails>
    <OrderID>10266</OrderID>
    <UnitPrice>30.4000</UnitPrice>
    <Quantity>12</Quantity>
    <Discount>0.05</Discount>
    <ProductName>Queso Manchego La Pastora</ProductName>
  </OrderDetails>
  <OrderDetails>
    <OrderID>10270</OrderID>
    <UnitPrice>15.2000</UnitPrice>
    <Quantity>30</Quantity>
    <Discount>0</Discount>
    <ProductName>Inlagd Sill</ProductName>
  </OrderDetails>
  <OrderDetails>
    <OrderID>10270</OrderID>
    <UnitPrice>36.8000</UnitPrice>
    <Quantity>25</Quantity>
    <Discount>0</Discount>
    <ProductName>Ipoh Coffee</ProductName>
  </OrderDetails>
  <OrderDetails>
    <OrderID>10320</OrderID>
    <UnitPrice>17.2000</UnitPrice>
    <Quantity>30</Quantity>
    <Discount>0</Discount>
    <ProductName>Flotemysost</ProductName>
  </OrderDetails>
  <OrderDetails>
    <OrderID>10333</OrderID>
    <UnitPrice>8.0000</UnitPrice>
    <Quantity>10</Quantity>
    <Discount>0.1</Discount>
    <ProductName>Sir Rodney's Scones</ProductName>
  </OrderDetails>
  <OrderDetails>
    <OrderID>10333</OrderID>
    <UnitPrice>18.6000</UnitPrice>
    <Quantity>10</Quantity>
    <Discount>0</Discount>
    <ProductName>Tofu</ProductName>
  </OrderDetails>
  <OrderDetails>
    <OrderID>10333</OrderID>
    <UnitPrice>17.2000</UnitPrice>
    <Quantity>40</Quantity>
    <Discount>0.1</Discount>
    <ProductName>Flotemysost</ProductName>
  </OrderDetails>
  <OrderDetails>
    <OrderID>10412</OrderID>
    <UnitPrice>18.6000</UnitPrice>
    <Quantity>20</Quantity>
    <Discount>0.1</Discount>
    <ProductName>Tofu</ProductName>
  </OrderDetails>
  <OrderDetails>
    <OrderID>10416</OrderID>
    <UnitPrice>26.2000</UnitPrice>
    <Quantity>10</Quantity>
    <Discount>0</Discount>
    <ProductName>Perth Pasties</ProductName>
  </OrderDetails>
  <OrderDetails>
    <OrderID>10416</OrderID>
    <UnitPrice>15.6000</UnitPrice>
    <Quantity>20</Quantity>
    <Discount>0</Discount>
    <ProductName>Ravioli Angelo</ProductName>
  </OrderDetails>
  <OrderDetails>
    <OrderID>10416</OrderID>
    <UnitPrice>7.3000</UnitPrice>
    <Quantity>20</Quantity>
    <Discount>0</Discount>
    <ProductName>Teatime Chocolate Biscuits</ProductName>
  </OrderDetails>
</DataSet1>
